lldb/__init__.py
lldb/_lldb.cpython-314-riscv64-linux-gnu.so
lldb/embedded_interpreter.py
lldb/formatters/Logger.py
lldb/formatters/__init__.py
lldb/formatters/attrib_fromdict.py
lldb/formatters/cache.py
lldb/formatters/metrics.py
lldb/formatters/synth.py
lldb/formatters/cpp/__init__.py
lldb/formatters/cpp/gnu_libstdcpp.py
lldb/formatters/cpp/libcxx.py
lldb/plugins/__init__.py
lldb/plugins/operating_system.py
lldb/plugins/parsed_cmd.py
lldb/plugins/scripted_platform.py
lldb/plugins/scripted_process.py
lldb/plugins/scripted_thread_plan.py
lldb/utils/__init__.py
lldb/utils/in_call_stack.py
lldb/utils/symbolication.py
lldb_for_pwndbg/__init__.py
lldb_for_pwndbg/lldb.py
lldb_for_pwndbg/lldb_server.py
lldb_for_pwndbg/_vendor/bin/lldb
lldb_for_pwndbg/_vendor/bin/lldb-server
lldb_for_pwndbg-21.1.7.post1.dist-info/METADATA
lldb_for_pwndbg-21.1.7.post1.dist-info/WHEEL
lldb_for_pwndbg-21.1.7.post1.dist-info/entry_points.txt
lldb_for_pwndbg-21.1.7.post1.dist-info/top_level.txt
lldb_for_pwndbg-21.1.7.post1.dist-info/RECORD
