Metadata-Version: 2.4
Name: lldb-for-pwndbg
Version: 21.1.7.post1
Summary: Prebuilt LLDB binaries for Pwndbg, ensuring reliable debugger integration, autocompletion, and IDE support.
Home-page: https://github.com/pwndbg/pypi-for-pwndbg
Project-URL: Bug Reports, https://github.com/pwndbg/pypi-for-pwndbg/issues
Project-URL: Source, https://github.com/pwndbg/pypi-for-pwndbg/
Requires-Python: >=3.10, <4
Dynamic: home-page
Dynamic: project-url
Dynamic: requires-python
Dynamic: summary
